CHANGELOG.md
CONTRIBUTING.md
LICENSE
MANIFEST.in
README.md
pyproject.toml
setup.cfg
setup.py
better_pyenv/__init__.py
better_pyenv.egg-info/PKG-INFO
better_pyenv.egg-info/SOURCES.txt
better_pyenv.egg-info/dependency_links.txt
better_pyenv.egg-info/not-zip-safe
better_pyenv.egg-info/requires.txt
better_pyenv.egg-info/top_level.txt