Metadata-Version: 2.1
Name: better-pyenv
Version: 9.5.0
Summary: simplified environment variable parsing
Author: Hung Dean
Author-email: hngdean@gmail.com
License: MIT
Keywords: environment variables parsing config configuration 12factor envvars
Platform: UNKNOWN
Classifier: Intended Audience :: Developers
Classifier: License :: OSI Approved :: MIT License
Classifier: Natural Language :: English
Classifier: Programming Language :: Python :: 3
Classifier: Programming Language :: Python :: 3.7
Classifier: Programming Language :: Python :: 3.8
Classifier: Programming Language :: Python :: 3.9
Classifier: Programming Language :: Python :: 3.10
Classifier: Typing :: Typed
Requires-Python: >=3.7
Provides-Extra: django
Provides-Extra: tests
Provides-Extra: lint
Provides-Extra: dev
License-File: LICENSE
